arbok_inspector/__init__.py
arbok_inspector/dev.py
arbok_inspector/main.py
arbok_inspector/state.py
arbok_inspector/analysis/analysis_base.py
arbok_inspector/analysis/prepare_data.py
arbok_inspector/classes/base_run.py
arbok_inspector/classes/dim.py
arbok_inspector/classes/native_run.py
arbok_inspector/classes/qcodes_run.py
arbok_inspector/configurations/1d_plot.json
arbok_inspector/configurations/2d_plot.json
arbok_inspector/helpers/string_formaters.py
arbok_inspector/helpers/unit_formater.py
arbok_inspector/pages/__init__.py
arbok_inspector/pages/database_browser.py
arbok_inspector/pages/greeter.py
arbok_inspector/pages/run_view.py
arbok_inspector/widgets/build_run_view_actions.py
arbok_inspector/widgets/build_xarray_grid.py
arbok_inspector/widgets/build_xarray_html.py
arbok_inspector/widgets/day_selector.py
arbok_inspector/widgets/json_plot_settings_dialog.py
arbok_inspector/widgets/run_selector.py
arbok_inspector-1.3.11.dist-info/METADATA
arbok_inspector-1.3.11.dist-info/WHEEL
arbok_inspector-1.3.11.dist-info/entry_points.txt
arbok_inspector-1.3.11.dist-info/top_level.txt
arbok_inspector-1.3.11.dist-info/RECORD
