Metadata-Version: 2.4
Name: arbok-inspector
Version: 1.3.11
Summary: Browser based QCoDeS database inspector
License: MIT
Classifier: Programming Language :: Python :: 3.12
Requires-Python: >=3.12
Requires-Dist: minio~=7.2
Requires-Dist: nicegui>=2.24.2
Requires-Dist: nodejs>=0.1.1
Requires-Dist: plotly>=6.3.0
Requires-Dist: psycopg2-binary~=2.9
Requires-Dist: s3fs~=2025.9
Requires-Dist: SQLAlchemy~=2.0
Requires-Dist: qcodes>=0.53.0
Requires-Dist: xarray>=2025.9.0
Requires-Dist: zarr~=2.18
